pera_wallet/__init__.py
pera_wallet/example.py
pera_wallet/py.typed
pera_wallet/frontend/build/asset-manifest.json
pera_wallet/frontend/build/bootstrap.min.css
pera_wallet/frontend/build/index.html
pera_wallet/frontend/build/static/css/main.477f696e.css
pera_wallet/frontend/build/static/css/main.477f696e.css.map
pera_wallet/frontend/build/static/css/main.5f4f55ec.css
pera_wallet/frontend/build/static/css/main.5f4f55ec.css.map
pera_wallet/frontend/build/static/css/main.952619af.css
pera_wallet/frontend/build/static/css/main.952619af.css.map
pera_wallet/frontend/build/static/js/main.20f41973.js
pera_wallet/frontend/build/static/js/main.20f41973.js.LICENSE.txt
pera_wallet/frontend/build/static/js/main.20f41973.js.map
pera_wallet/frontend/build/static/js/main.2400543d.js
pera_wallet/frontend/build/static/js/main.2400543d.js.LICENSE.txt
pera_wallet/frontend/build/static/js/main.2400543d.js.map
pera_wallet/frontend/build/static/js/main.33890d90.js
pera_wallet/frontend/build/static/js/main.33890d90.js.LICENSE.txt
pera_wallet/frontend/build/static/js/main.33890d90.js.map
pera_wallet/frontend/build/static/js/main.3aa314dd.js
pera_wallet/frontend/build/static/js/main.3aa314dd.js.LICENSE.txt
pera_wallet/frontend/build/static/js/main.3aa314dd.js.map
pera_wallet/frontend/build/static/js/main.62457a4c.js
pera_wallet/frontend/build/static/js/main.62457a4c.js.LICENSE.txt
pera_wallet/frontend/build/static/js/main.62457a4c.js.map
pera_wallet/frontend/build/static/js/main.9caae159.js
pera_wallet/frontend/build/static/js/main.9caae159.js.LICENSE.txt
pera_wallet/frontend/build/static/js/main.9caae159.js.map
pera_wallet/frontend/build/static/js/main.bb7f3756.js
pera_wallet/frontend/build/static/js/main.bb7f3756.js.LICENSE.txt
pera_wallet/frontend/build/static/js/main.bb7f3756.js.map
pera_wallet/frontend/build/static/js/main.f8470511.js
pera_wallet/frontend/build/static/js/main.f8470511.js.LICENSE.txt
pera_wallet/frontend/build/static/js/main.f8470511.js.map
pera_wallet-0.0.16.dist-info/LICENSE
pera_wallet-0.0.16.dist-info/METADATA
pera_wallet-0.0.16.dist-info/WHEEL
pera_wallet-0.0.16.dist-info/top_level.txt
pera_wallet-0.0.16.dist-info/RECORD
