Metadata-Version: 2.1
Name: pera_wallet
Version: 0.0.16
Summary: Streamlit component that allows you to connect to Pera Wallet.
Home-page: 
Author: code-alexander
Author-email: 
Requires-Python: >=3.11
License-File: LICENSE
Requires-Dist: streamlit>=1.41
Provides-Extra: devel
Requires-Dist: wheel; extra == "devel"
Requires-Dist: pytest==7.4.0; extra == "devel"
Requires-Dist: playwright==1.48.0; extra == "devel"
Requires-Dist: requests==2.31.0; extra == "devel"
Requires-Dist: pytest-playwright-snapshot==1.0; extra == "devel"
Requires-Dist: pytest-rerunfailures==12.0; extra == "devel"
